patra_model_card/__init__.py
patra_model_card/fairlearn_bias.py
patra_model_card/patra_model_card.py
patra_model_card/shap_xai.py
patra_model_card/schema/schema.json
tests/__init__.py
tests/test_patra_hash_id.py
tests/test_patra_inout_data.py
tests/test_patra_mc.py
patra_model_card-0.1.1.dist-info/LICENSE
patra_model_card-0.1.1.dist-info/METADATA
patra_model_card-0.1.1.dist-info/WHEEL
patra_model_card-0.1.1.dist-info/top_level.txt
patra_model_card-0.1.1.dist-info/RECORD
