Metadata-Version: 2.1
Name: patra_model_card
Version: 0.1.1
Summary: Patra Model Card Toolkit
Home-page: https://github.com/Data-to-Insight-Center/patra-toolkit.git
Author: Data to Insight Center
Author-email: d2i@iu.edu
License: BSD-3-Clause
License-File: LICENSE
Requires-Dist: attrs~=23.1.0
Requires-Dist: jsonschema~=4.18.6
Requires-Dist: fairlearn~=0.11.0
Requires-Dist: scipy~=1.13.1
Requires-Dist: scikit-learn~=1.5.0
Requires-Dist: shap~=0.46.0
Requires-Dist: pandas~=2.2.3
Requires-Dist: numpy<=2.1.3
Requires-Dist: pyrsistent~=0.19.3
Requires-Dist: requests>=2.32.3
